csspin/__init__.py
csspin/__main__.py
csspin/cli.py
csspin/schema.py
csspin/schema.yaml
csspin/tree.py
csspin/builtin/__init__.py
csspin-3.0.0.dist-info/licenses/LICENSE
csspin-3.0.0.dist-info/METADATA
csspin-3.0.0.dist-info/WHEEL
csspin-3.0.0.dist-info/entry_points.txt
csspin-3.0.0.dist-info/top_level.txt
csspin-3.0.0.dist-info/RECORD
