Metadata-Version: 2.4
Name: csspin
Version: 3.0.0
Summary: Spin is a task runner that aims to solve the problems of provisioning development environments and standardizing workflows.
Author-email: CONTACT Software GmbH <info@contact-software.com>, Frank Patz-Brockmann <frank.patz-brockmann@contact-software.com>
Maintainer-email: Waleri Enns <waleri.enns@contact-software.com>, Benjamin Thomas Schwertfeger <benjaminthomas.schwertfeger@contact-software.com>, Fabian Hafer <fabian.hafer@contact-software.com>
License-Expression: Apache-2.0
Project-URL: CONTACT Software GmbH, https://contact-software.com
Project-URL: Documentation, https://csspin.readthedocs.io/en/stable/
Project-URL: Issue Tracker, https://github.com/cslab/csspin/issues
Project-URL: Release Notes, https://csspin.readthedocs.io/en/stable/relnotes.html
Project-URL: Repository, https://github.com/cslab/csspin
Classifier: Environment :: Console
Classifier: Development Status :: 5 - Production/Stable
Classifier: Intended Audience :: Developers
Classifier: Operating System :: OS Independent
Classifier: Programming Language :: Python :: 3
Classifier: Programming Language :: Python :: 3.10
Classifier: Programming Language :: Python :: 3.11
Classifier: Programming Language :: Python :: 3.12
Classifier: Programming Language :: Python :: 3.13
Classifier: Programming Language :: Python :: 3.14
Classifier: Topic :: Software Development
Requires-Python: >=3.10
License-File: LICENSE
Requires-Dist: click~=8.1.8
Requires-Dist: distro~=1.9.0
Requires-Dist: packaging~=25.0
Requires-Dist: path~=17.0.0
Requires-Dist: pip>=22.0
Requires-Dist: platformdirs~=4.3.8
Requires-Dist: ruamel.yaml~=0.18.10
Dynamic: license-file
